passcrow/__init__.py
passcrow/__main__.py
passcrow/aes_utils.py
passcrow/client.py
passcrow/messages.py
passcrow/mock.py
passcrow/mon.py
passcrow/payments.py
passcrow/proto.py
passcrow/secret_share.py
passcrow/server.py
passcrow/storage.py
passcrow/util.py
passcrow/handlers/__init__.py
passcrow/handlers/email.py
passcrow/handlers/tel.py
passcrow/handlers/twilio.py
passcrow/handlers/validators.py
passcrow/integration/flask_app.py
passcrow/integration/flask_common.py
passcrow/integration/upagekite_app.py
passcrow-0.0.7.dist-info/LICENSE.txt
passcrow-0.0.7.dist-info/METADATA
passcrow-0.0.7.dist-info/WHEEL
passcrow-0.0.7.dist-info/entry_points.txt
passcrow-0.0.7.dist-info/top_level.txt
passcrow-0.0.7.dist-info/RECORD
